ogmmlopsticket1_pkg/__init__.py
ogmmlopsticket1_pkg/dpp.py
ogmtk1-0.0.1.dist-info/METADATA
ogmtk1-0.0.1.dist-info/WHEEL
ogmtk1-0.0.1.dist-info/entry_points.txt
ogmtk1-0.0.1.dist-info/top_level.txt
ogmtk1-0.0.1.dist-info/RECORD
