Metadata-Version: 2.1
Name: ogmtk1
Version: 0.0.1
Summary: Project for ticket 1
Home-page: https://github.com/mksaraf/ogm.mlops.github.ticket.1.git
Author: Manish Kumar Saraf
Author-email: manish.saraf@ogmworldwide.com
Classifier: Programming Language :: Python :: 3
Classifier: License :: OSI Approved :: MIT License
Classifier: Operating System :: OS Independent
Requires-Python: >=3.7
